{
    "/js/app.js": "/js/app.js",
    "/css/app.css": "/css/app.css",
    "/0.6d9ee274d5b4ed900c2e.hot-update.js": "/0.6d9ee274d5b4ed900c2e.hot-update.js",
    "/0.8458955e30d765f0fc64.hot-update.js": "/0.8458955e30d765f0fc64.hot-update.js",
    "/0.14d7f53f91fcd27b6ed9.hot-update.js": "/0.14d7f53f91fcd27b6ed9.hot-update.js",
    "/0.4675868c8c47b86dfba7.hot-update.js": "/0.4675868c8c47b86dfba7.hot-update.js",
    "/0.da2d291733962d262f1e.hot-update.js": "/0.da2d291733962d262f1e.hot-update.js",
    "/0.367894025d4735d582de.hot-update.js": "/0.367894025d4735d582de.hot-update.js",
    "/0.5136016863bf93263ffe.hot-update.js": "/0.5136016863bf93263ffe.hot-update.js",
    "/0.0b04edab42e8dba65602.hot-update.js": "/0.0b04edab42e8dba65602.hot-update.js",
    "/0.c8d58229eb94bcc4f860.hot-update.js": "/0.c8d58229eb94bcc4f860.hot-update.js",
    "/0.37f36be23bd6040757bc.hot-update.js": "/0.37f36be23bd6040757bc.hot-update.js",
    "/0.04255e16e19d608db09d.hot-update.js": "/0.04255e16e19d608db09d.hot-update.js",
    "/0.edec19ddc8e517d06e77.hot-update.js": "/0.edec19ddc8e517d06e77.hot-update.js",
    "/0.88a2a9027171cf0c4259.hot-update.js": "/0.88a2a9027171cf0c4259.hot-update.js",
    "/0.a54eff37e5621ca73ae1.hot-update.js": "/0.a54eff37e5621ca73ae1.hot-update.js",
    "/0.6f30e91015eff2edab2b.hot-update.js": "/0.6f30e91015eff2edab2b.hot-update.js",
    "/0.bf490b6db1240079c4aa.hot-update.js": "/0.bf490b6db1240079c4aa.hot-update.js",
    "/0.09b957d995b24e475669.hot-update.js": "/0.09b957d995b24e475669.hot-update.js",
    "/0.1330aa525220ca53ee78.hot-update.js": "/0.1330aa525220ca53ee78.hot-update.js",
    "/0.9110b0e3e732985b7656.hot-update.js": "/0.9110b0e3e732985b7656.hot-update.js",
    "/0.fd2fb107afd9fdded841.hot-update.js": "/0.fd2fb107afd9fdded841.hot-update.js",
    "/0.53c602eecc4cf2f50941.hot-update.js": "/0.53c602eecc4cf2f50941.hot-update.js",
    "/0.f968250415674dd1bbd6.hot-update.js": "/0.f968250415674dd1bbd6.hot-update.js",
    "/0.b95b00ab96e3b433c88d.hot-update.js": "/0.b95b00ab96e3b433c88d.hot-update.js",
    "/0.9376db9eb6c21082efa4.hot-update.js": "/0.9376db9eb6c21082efa4.hot-update.js",
    "/0.d095f5d9450420a1e925.hot-update.js": "/0.d095f5d9450420a1e925.hot-update.js",
    "/0.95f0073f084bc6b39f97.hot-update.js": "/0.95f0073f084bc6b39f97.hot-update.js",
    "/0.b73e65206b11d4b14c72.hot-update.js": "/0.b73e65206b11d4b14c72.hot-update.js",
    "/0.7e191c963e6b53f09de8.hot-update.js": "/0.7e191c963e6b53f09de8.hot-update.js",
    "/0.3bd7c1c6c50a3e9289b9.hot-update.js": "/0.3bd7c1c6c50a3e9289b9.hot-update.js",
    "/0.b77b447c0c4d9fd20818.hot-update.js": "/0.b77b447c0c4d9fd20818.hot-update.js",
    "/0.b5409a73d43c1cbc87a4.hot-update.js": "/0.b5409a73d43c1cbc87a4.hot-update.js",
    "/0.01cdd8d36b308a0f4c18.hot-update.js": "/0.01cdd8d36b308a0f4c18.hot-update.js",
    "/0.abf2da5aec1950a328ea.hot-update.js": "/0.abf2da5aec1950a328ea.hot-update.js",
    "/0.3a6454168b3a8df65444.hot-update.js": "/0.3a6454168b3a8df65444.hot-update.js",
    "/0.9df7f814214122a7b7e5.hot-update.js": "/0.9df7f814214122a7b7e5.hot-update.js",
    "/0.d4b07fd41e968a7a75b4.hot-update.js": "/0.d4b07fd41e968a7a75b4.hot-update.js",
    "/0.034de6d97dc7da186d62.hot-update.js": "/0.034de6d97dc7da186d62.hot-update.js",
    "/0.2fa58d31ef8de2cc8211.hot-update.js": "/0.2fa58d31ef8de2cc8211.hot-update.js"
}